aliyunsdknlb/__init__.py
aliyunsdknlb/endpoint.py
aliyunsdknlb/request/__init__.py
aliyunsdknlb/request/v20220430/AddServersToServerGroupRequest.py
aliyunsdknlb/request/v20220430/AssociateAdditionalCertificatesWithListenerRequest.py
aliyunsdknlb/request/v20220430/AttachCommonBandwidthPackageToLoadBalancerRequest.py
aliyunsdknlb/request/v20220430/CancelShiftLoadBalancerZonesRequest.py
aliyunsdknlb/request/v20220430/CreateListenerRequest.py
aliyunsdknlb/request/v20220430/CreateLoadBalancerRequest.py
aliyunsdknlb/request/v20220430/CreateSecurityPolicyRequest.py
aliyunsdknlb/request/v20220430/CreateServerGroupRequest.py
aliyunsdknlb/request/v20220430/DeleteListenerRequest.py
aliyunsdknlb/request/v20220430/DeleteLoadBalancerRequest.py
aliyunsdknlb/request/v20220430/DeleteSecurityPolicyRequest.py
aliyunsdknlb/request/v20220430/DeleteServerGroupRequest.py
aliyunsdknlb/request/v20220430/DescribeRegionsRequest.py
aliyunsdknlb/request/v20220430/DescribeZonesRequest.py
aliyunsdknlb/request/v20220430/DetachCommonBandwidthPackageFromLoadBalancerRequest.py
aliyunsdknlb/request/v20220430/DisableLoadBalancerIpv6InternetRequest.py
aliyunsdknlb/request/v20220430/DisassociateAdditionalCertificatesWithListenerRequest.py
aliyunsdknlb/request/v20220430/EnableLoadBalancerIpv6InternetRequest.py
aliyunsdknlb/request/v20220430/GetJobStatusRequest.py
aliyunsdknlb/request/v20220430/GetListenerAttributeRequest.py
aliyunsdknlb/request/v20220430/GetListenerHealthStatusRequest.py
aliyunsdknlb/request/v20220430/GetLoadBalancerAttributeRequest.py
aliyunsdknlb/request/v20220430/ListListenerCertificatesRequest.py
aliyunsdknlb/request/v20220430/ListListenersRequest.py
aliyunsdknlb/request/v20220430/ListLoadBalancersRequest.py
aliyunsdknlb/request/v20220430/ListSecurityPolicyRequest.py
aliyunsdknlb/request/v20220430/ListServerGroupServersRequest.py
aliyunsdknlb/request/v20220430/ListServerGroupsRequest.py
aliyunsdknlb/request/v20220430/ListSystemSecurityPolicyRequest.py
aliyun_python_sdk_nlb-1.0.12.dist-info/LICENSE
aliyun_python_sdk_nlb-1.0.12.dist-info/METADATA
aliyun_python_sdk_nlb-1.0.12.dist-info/WHEEL
aliyun_python_sdk_nlb-1.0.12.dist-info/top_level.txt
aliyun_python_sdk_nlb-1.0.12.dist-info/RECORD
